tabularforge/__init__.py
tabularforge/forge.py
tabularforge/generators/__init__.py
tabularforge/generators/base.py
tabularforge/generators/copula.py
tabularforge/generators/ctgan.py
tabularforge/generators/tvae.py
tabularforge/metrics/__init__.py
tabularforge/metrics/privacy.py
tabularforge/metrics/statistical.py
tabularforge/metrics/utility.py
tabularforge/preprocessing/__init__.py
tabularforge/preprocessing/encoder.py
tabularforge/preprocessing/transformer.py
tabularforge/privacy/__init__.py
tabularforge/privacy/attacks.py
tabularforge/privacy/differential.py
tabularforge/utils/__init__.py
tabularforge_sgk-0.1.1.dist-info/licenses/LICENSE
tabularforge_sgk-0.1.1.dist-info/METADATA
tabularforge_sgk-0.1.1.dist-info/WHEEL
tabularforge_sgk-0.1.1.dist-info/top_level.txt
tabularforge_sgk-0.1.1.dist-info/RECORD
