Metadata-Version: 2.4
Name: tabularforge-sgk
Version: 0.1.1
Summary: Privacy-Preserving Synthetic Tabular Data Generation
Author-email: Sai Ganesh Kolan <aiganesh1299@gmail.com>
Maintainer-email: Sai Ganesh Kolan <aiganesh1299@gmail.com>
License: MIT
Project-URL: Homepage, https://github.com/ganeshreddy28/tabularforge
Project-URL: Documentation, https://tabularforge.readthedocs.io
Project-URL: Repository, https://github.com/ganeshreddy28/tabularforge
Project-URL: Issues, https://github.com/ganeshreddy28/tabularforge
Project-URL: Changelog, https://github.com/ganeshreddy28/tabularforge/blob/main/CHANGELOG.md
Keywords: synthetic-data,tabular-data,privacy,differential-privacy,machine-learning,data-generation,GAN,CTGAN,VAE,data-augmentation,GDPR,HIPAA
Classifier: Development Status :: 4 - Beta
Classifier: Intended Audience :: Developers
Classifier: Intended Audience :: Science/Research
Classifier: Intended Audience :: Healthcare Industry
Classifier: Intended Audience :: Financial and Insurance Industry
Classifier: License :: OSI Approved :: MIT License
Classifier: Operating System :: OS Independent
Classifier: Programming Language :: Python :: 3
Classifier: Programming Language :: Python :: 3.8
Classifier: Programming Language :: Python :: 3.9
Classifier: Programming Language :: Python :: 3.10
Classifier: Programming Language :: Python :: 3.11
Classifier: Programming Language :: Python :: 3.12
Classifier: Topic :: Scientific/Engineering :: Artificial Intelligence
Classifier: Topic :: Scientific/Engineering :: Information Analysis
Classifier: Topic :: Security :: Cryptography
Classifier: Typing :: Typed
Requires-Python: >=3.8
License-File: LICENSE
Requires-Dist: numpy>=1.21.0
Requires-Dist: pandas>=1.3.0
Requires-Dist: scikit-learn>=1.0.0
Requires-Dist: scipy>=1.7.0
Requires-Dist: torch>=1.9.0
Provides-Extra: dev
Requires-Dist: pytest>=7.0.0; extra == "dev"
Requires-Dist: pytest-cov>=4.0.0; extra == "dev"
Requires-Dist: black>=23.0.0; extra == "dev"
Requires-Dist: flake8>=6.0.0; extra == "dev"
Requires-Dist: isort>=5.12.0; extra == "dev"
Requires-Dist: mypy>=1.0.0; extra == "dev"
Requires-Dist: pre-commit>=3.0.0; extra == "dev"
Provides-Extra: docs
Requires-Dist: sphinx>=6.0.0; extra == "docs"
Requires-Dist: sphinx-rtd-theme>=1.2.0; extra == "docs"
Requires-Dist: myst-parser>=1.0.0; extra == "docs"
Provides-Extra: viz
Requires-Dist: matplotlib>=3.5.0; extra == "viz"
Requires-Dist: seaborn>=0.12.0; extra == "viz"
Provides-Extra: all
Requires-Dist: tabularforge[dev,docs,viz]; extra == "all"
Dynamic: license-file
